<?xml version="1.0" encoding="utf-8" ?>
<hibernate-mapping xmlns="urn:nhibernate-mapping-2.2" default-lazy="true" namespace="DBUpdater.Tables" assembly="DBUpdater">
	<class name="FofFranchise,DBUpdater" table="fof_franchise" lazy="true">

		<!-- Primary Key(s) -->
		<id name="_Id" column="ID" type="Int16" unsaved-value="0">
			<generator class="native"/>
		</id>
		
		<!-- Properties -->
		<property column="TeamIndex" type="Byte" name="_TeamIndex" not-null="true" />
		<property column="Year" type="Int16" name="_Year" not-null="true" />
		<property column="FranchiseValue" type="Byte" name="_FranchiseValue" not-null="true" />
		<property column="ProfitScore" type="Byte" name="_ProfitScore" not-null="true" />
		<property column="PerformanceScore" type="Byte" name="_PerformanceScore" not-null="true" />
		<property column="RosterScore" type="Byte" name="_RosterScore" not-null="true" />
		<property column="Playoffs" type="Byte" name="_Playoffs" not-null="true" />
		<property column="Wins" type="Byte" name="_Wins" not-null="true" />
		<property column="Losses" type="Byte" name="_Losses" not-null="true" />
		<property column="Ties" type="Byte" name="_Ties" not-null="true" />
		<property column="PointsFor" type="Int16" name="_PointsFor" not-null="true" />
		<property column="PointsAgainst" type="Int16" name="_PointsAgainst" not-null="true" />
		<property column="ConfWins" type="Byte" name="_ConfWins" not-null="true" />
		<property column="ConfLoss" type="Byte" name="_ConfLoss" not-null="true" />
		<property column="ConfTies" type="Byte" name="_ConfTies" not-null="true" />
		<property column="DivWin" type="Byte" name="_DivWin" not-null="true" />
		<property column="DivLoss" type="Byte" name="_DivLoss" not-null="true" />
		<property column="DivTie" type="Byte" name="_DivTie" not-null="true" />
		<property column="Attendance" type="Int32" name="_Attendance" not-null="true" />
		<property column="StadiumCapacity" type="Int32" name="_StadiumCapacity" not-null="true" />
		<property column="TVRevenue" type="Int64" name="_TvRevenue" not-null="true" />
		<property column="TicketRevenue" type="Int64" name="_TicketRevenue" not-null="true" />
		<property column="SuiteRevenue" type="Int64" name="_SuiteRevenue" not-null="true" />
		<property column="PlayerSalaries" type="Int64" name="_PlayerSalaries" not-null="true" />
		<property column="PlayerBonuses" type="Int64" name="_PlayerBonuses" not-null="true" />
		<property column="StadiumPayment" type="Int64" name="_StadiumPayment" not-null="true" />
		<property column="Concessions" type="Int64" name="_Concessions" not-null="true" />
		<property column="Parking" type="Int64" name="_Parking" not-null="true" />
		<property column="Advertising" type="Int64" name="_Advertising" not-null="true" />
		<property column="Training" type="Int64" name="_Training" not-null="true" />
		<property column="Coaching" type="Int64" name="_Coaching" not-null="true" />
		<property column="Scouting" type="Int64" name="_Scouting" not-null="true" />
		<property column="Maintenance" type="Int64" name="_Maintenance" not-null="true" />
		
	</class>
</hibernate-mapping>
