<?xml version="1.0" encoding="utf-8" ?>
<hibernate-mapping xmlns="urn:nhibernate-mapping-2.2" default-lazy="true" namespace="DBUpdater.Tables" assembly="DBUpdater">
	<class name="FofGamedrive,DBUpdater" table="fof_gamedrive" lazy="true">

		<!-- Primary Key(s) -->
		<id name="_Id" column="ID" type="Int32" unsaved-value="0">
			<generator class="native"/>
		</id>
		
		<!-- Properties -->
		<property column="StartQuarter" type="Byte" name="_StartQuarter" not-null="true" />
		<property column="StartMinutes" type="Byte" name="_StartMinutes" not-null="true" />
		<property column="StartSeconds" type="Byte" name="_StartSeconds" not-null="true" />
		<property column="EndQuarter" type="Byte" name="_EndQuarter" not-null="true" />
		<property column="EndMinutes" type="Byte" name="_EndMinutes" not-null="true" />
		<property column="EndSeconds" type="Byte" name="_EndSeconds" not-null="true" />
		<property column="StartYardsFromGoal" type="Byte" name="_StartYardsFromGoal" not-null="true" />
		<property column="PlayCount" type="Byte" name="_PlayCount" not-null="true" />
		<property column="YardsGained" type="Int16" name="_YardsGained" not-null="true" />
		<property column="Result" type="Byte" name="_Result" not-null="true" />
		<property column="GameID" type="Int32" name="_Gameid" not-null="true" />
		<property column="Team" type="Byte" name="_Team" not-null="true" />
		
	</class>
</hibernate-mapping>
